[
    {
        "id": 1,
        "name": "Front Flood Light",
        "device": 2,
        "instance": 0,
        "controllerHost": "192.168.10.221",
        "controllerPort": 8083
    },
    {
        "id": 2,
        "name": "Side Passage",
        "device": 3,
        "instance": 0,
        "controllerHost": "192.168.10.221",
        "controllerPort": 8083
    },
    {
        "id": 3,
        "name": "Art Room",
        "device": 4,
        "instance": 0,
        "controllerHost": "192.168.10.221",
        "controllerPort": 8083
    },
    {
        "id": 4,
        "name": "Front Lounge",
        "device": 5,
        "instance": 1,
        "controllerHost": "192.168.10.221",
        "controllerPort": 8083
    },
    {
        "id": 5,
        "name": "Man Cave",
        "device": 2,
        "instance": 0,
        "controllerHost": "192.168.10.223",
        "controllerPort": 8083
    }
]